fdman/__init__.py
fdman/fdman.py
fdman/utils.py
fdman_cli-0.1.1.dist-info/METADATA
fdman_cli-0.1.1.dist-info/WHEEL
fdman_cli-0.1.1.dist-info/entry_points.txt
fdman_cli-0.1.1.dist-info/top_level.txt
fdman_cli-0.1.1.dist-info/RECORD
