Metadata-Version: 2.1
Name: fdman-cli
Version: 0.1.1
Summary: A CLI tool that manages files and directories.
Home-page: https://github.com/ayoub-aberbach/fdman
Author: Ayoub A.
Author-email: Ayoub Aberbach <aberbach.me@gmail.com>
Maintainer-email: Ayoub Aberbach <aberbach.me@gmail.com>
Project-URL: Repository, https://github.com/ayoub-aberbach/fdman
Requires-Python: >=3.6
Requires-Dist: click
Requires-Dist: colorama
Requires-Dist: importlib-metadata; python_version < "3.12"
